Metadata-Version: 1.1
Name: controlid
Version: 0.1.0
Summary: Cli to handle open door
Home-page: UNKNOWN
Author: jadson179
Author-email: UNKNOWN
License: MIT
Platform: UNKNOWN
Classifier: Programming Language :: Python
Classifier: Programming Language :: Python :: 3.8
